<svg xmlns='http://www.w3.org/2000/svg' xmlns:th="http://www.thymeleaf.org" width='106.25' height='20'>
    <linearGradient id='a' x2='0' y2='100%'>
        <stop offset='0' stop-color='#bbb' stop-opacity='0.1' />
        <stop offset='1' stop-opacity='0.1' />
    </linearGradient>
    <rect rx='3' width='106.25' height='20' fill='#555' />
    <rect rx='3' x='47' width='59.25' height='20' fill='#9f9f9f' />
    <path fill='#9f9f9f' d='M47 0h4v20h-4z' />
    <rect rx='3' width='106.25' height='20' fill='url(#a)' />
    <g fill='#fff' text-anchor='middle' font-family='DejaVu Sans,Verdana,Geneva,sans-serif' font-size='11'>
        <text x='23.5' y='15' fill='#010101' fill-opacity='0.3'>Gradle</text>
        <text x='23.5' y='14'>Gradle</text>
        <text x='75.625' y='15' fill='#010101' fill-opacity='0.3' th:text="${status}"/>
        <text x='75.625' y='14' th:text="${status}"/>
    </g>
</svg>